neurone/Debug.py
neurone/__init__.py
Rajasthan-0.0.1.dist-info/LICENSE.text
Rajasthan-0.0.1.dist-info/METADATA
Rajasthan-0.0.1.dist-info/WHEEL
Rajasthan-0.0.1.dist-info/top_level.txt
Rajasthan-0.0.1.dist-info/RECORD
